.gitignore
LICENSE
Makefile
README.rst
setup.py
examples/Access Examples.ipynb
metatabdecl/Makefile
metatabdecl/__init__.py
metatabdecl/datapackage-0.1.csv
metatabdecl/datapackage-0.1.json
metatabdecl/datapackage-latest.csv
metatabdecl/datapackage-latest.json
metatabdecl/datapackage.csv
metatabdecl/datapackage.json
metatabdecl/metatab-0.1.csv
metatabdecl/metatab-0.1.json
metatabdecl/metatab-0.2.csv
metatabdecl/metatab-0.2.json
metatabdecl/metatab-latest.csv
metatabdecl/metatab-latest.json
metatabdecl.egg-info/PKG-INFO
metatabdecl.egg-info/SOURCES.txt
metatabdecl.egg-info/dependency_links.txt
metatabdecl.egg-info/not-zip-safe
metatabdecl.egg-info/top_level.txt
specs/Data Package Interoperability.md
specs/Metatab Packages.md
specs/Metatab Specification.md