Metadata-Version: 1.0
Name: metatabdecl
Version: 1.7
Summary: Declaration files and specifications for the Metatab package
Home-page: https://github.com/Metatab/metatab-declarations
Author: Eric Busboom
Author-email: eric@busboom.org
License: BSD 2-Clause License
Platform: UNKNOWN
